mvpdlite/MVPD_lin_reg.py
mvpdlite/__init__.py
mvpdlite/avgrun_regression.py
mvpdlite/data_loading.py
mvpdlite/dim_red.py
mvpdlite/model_exec.py
mvpdlite/params_check.py
mvpdlite/custom_func/__init__.py
mvpdlite/custom_func/dimred_custom.py
mvpdlite/dataloader/__init__.py
mvpdlite/dataloader/loader_regression.py
mvpdlite/dimension_reduction/__init__.py
mvpdlite/dimension_reduction/dimred_base.py
mvpdlite/evaluation/__init__.py
mvpdlite/evaluation/var_expl.py
mvpdlite/func_regression/__init__.py
mvpdlite/func_regression/lin_reg.py
mvpdlite/preprocessing/__init__.py
mvpdlite/preprocessing/dataset_processing.py
mvpdlite/viz/__init__.py
mvpdlite/viz/viz_map.py
PyMVPD_LITE-0.0.4.dist-info/LICENSE
PyMVPD_LITE-0.0.4.dist-info/METADATA
PyMVPD_LITE-0.0.4.dist-info/WHEEL
PyMVPD_LITE-0.0.4.dist-info/top_level.txt
PyMVPD_LITE-0.0.4.dist-info/RECORD
